jmap_client/__init__.py
jmap_client/client.py
jmap_client/exceptions.py
jmap_client/response.py
jmap_client/result.py
jmap_client-0.0.1.dist-info/METADATA
jmap_client-0.0.1.dist-info/WHEEL
jmap_client-0.0.1.dist-info/top_level.txt
jmap_client-0.0.1.dist-info/RECORD
