Metadata-Version: 2.1
Name: jmap-client
Version: 0.0.1
Summary: A client for speaking JMAP
Home-page: https://github.com/mmcclimon/python-jmap-client
Author: Michael McClimon
Author-email: michael@mcclimon.org
License: UNKNOWN
Platform: UNKNOWN
Requires-Python: >=3.6.3
Requires-Dist: requests (==2.21.0)
Requires-Dist: setuptools (==39.0.1)
